README.rst
native_app.py
setup.py
Pythonometer.egg-info/PKG-INFO
Pythonometer.egg-info/SOURCES.txt
Pythonometer.egg-info/dependency_links.txt
Pythonometer.egg-info/entry_points.txt
Pythonometer.egg-info/top_level.txt
pythonometer/__init__.py
pythonometer/quiz.py
pythonometer/questions/__init__.py
pythonometer/questions/base.py
pythonometer/questions/language/__init__.py
pythonometer/questions/language/compound_statements.py
pythonometer/questions/standard_library/__init__.py
pythonometer/questions/standard_library/built_in_exceptions.py
pythonometer/questions/standard_library/built_in_functions.py
pythonometer/questions/standard_library/built_in_types.py