Metadata-Version: 1.0
Name: Pythonometer
Version: 0.2.0
Summary: A tool for measuring and improving Python skills
Home-page: https://github.com/samuelfekete/Pythonometer
Author: Samuel Fekete
Author-email: UNKNOWN
License: UNKNOWN
Platform: UNKNOWN
